{
  "lightScheme": "minimal-default-light",
  "darkScheme": "minimal-atom-dark",
  "editorFont": "",
  "lineWidth": 42,
  "lineWidthWide": 88,
  "maxWidth": 100,
  "textNormal": 16,
  "textSmall": 13,
  "imgGrid": false,
  "devBlockWidth": false,
  "chartWidth": false,
  "tableWidth": true,
  "iframeWidth": true,
  "mapWidth": false,
  "borderColor": "minimal-border-faint",
  "colorfulFrame": false,
  "colorfulActiveStates": true,
  "colorfulHeadings": true,
  "trimFileName": true,
  "minimalFocus": false,
  "underlineInternal": false,
  "underlineExternal": true,
  "folding": true,
  "labeledNav": true
}
